AUTHORS.rst
CONTRIBUTING.rst
HISTORY.rst
LICENSE
MANIFEST.in
README.rst
setup.cfg
setup.py
docs/Makefile
docs/authors.rst
docs/conf.py
docs/contributing.rst
docs/history.rst
docs/index.rst
docs/installation.rst
docs/make.bat
docs/readme.rst
docs/usage.rst
logmetrics_sdk/__init__.py
logmetrics_sdk/logmetrics.py
logmetrics_sdk.egg-info/PKG-INFO
logmetrics_sdk.egg-info/SOURCES.txt
logmetrics_sdk.egg-info/dependency_links.txt
logmetrics_sdk.egg-info/entry_points.txt
logmetrics_sdk.egg-info/not-zip-safe
logmetrics_sdk.egg-info/requires.txt
logmetrics_sdk.egg-info/top_level.txt
logmetrics_sdk/common/__init__.py
logmetrics_sdk/common/logmetrics_config.py
logmetrics_sdk/common/message.py
logmetrics_sdk/patch/__init__.py
logmetrics_sdk/patch/patch.py
logmetrics_sdk/patch/requests/__init__.py
logmetrics_sdk/patch/requests/patch.py
logmetrics_sdk/utils/__init__.py
logmetrics_sdk/utils/constants.py
logmetrics_sdk/utils/importer.py
logmetrics_sdk/utils/json_util.py
logmetrics_sdk/utils/parse.py
logmetrics_sdk/utils/timer.py
tests/__init__.py
tests/test_logmetrics.py