Metadata-Version: 1.2
Name: logmetrics-sdk
Version: 1.0.2
Summary: LogMetrics provides simplified configuration to log payload for python projects
Home-page: https://github.com/devxchangeio/logmetrics-python
Author: devxchange.io
Author-email: info@devxchange.io
License: Apache Software License 2.0
Keywords: logmetrics-sdk
Platform: UNKNOWN
Classifier: Development Status :: 2 - Pre-Alpha
Classifier: Intended Audience :: Developers
Classifier: License :: OSI Approved :: Apache Software License
Classifier: Natural Language :: English
Classifier: Programming Language :: Python :: 2
Classifier: Programming Language :: Python :: 2.7
Classifier: Programming Language :: Python :: 3
Classifier: Programming Language :: Python :: 3.5
Classifier: Programming Language :: Python :: 3.6
Classifier: Programming Language :: Python :: 3.7
Classifier: Programming Language :: Python :: 3.8
Requires-Python: >=2.7, !=3.0.*, !=3.1.*, !=3.2.*, !=3.3.*, !=3.4.*
